stspy/__init__.py
stspy-1.0.3.dist-info/LICENSE.txt
stspy-1.0.3.dist-info/METADATA
stspy-1.0.3.dist-info/WHEEL
stspy-1.0.3.dist-info/top_level.txt
stspy-1.0.3.dist-info/RECORD
