Metadata-Version: 2.1
Name: stspy
Version: 1.0.3
Summary: Scanning Tunneling Spectra Analysis in Python
Home-page: UNKNOWN
Author: Dacen Waters and Joe Seifert
Author-email: dacen.c.waters@gmail.com
License: GNU GENERAL PUBLIC LICENSE
Platform: UNKNOWN
